frumpy/__init__.py
frumpy-1.0.4.dist-info/METADATA
frumpy-1.0.4.dist-info/WHEEL
frumpy-1.0.4.dist-info/top_level.txt
frumpy-1.0.4.dist-info/RECORD
