Metadata-Version: 2.1
Name: frumpy
Version: 1.0.4
Summary: It's FrumPy time.
Author: Frumpy
Author-email: frumpyfrumpster@gmail.com
License: UNKNOWN
Platform: UNKNOWN
Requires-Python: >=3.6
Requires-Dist: numpy
